reddit2pdf/__init__.py
reddit2pdf/__main__.py
reddit2pdf/bdfrjsonhelper.py
reddit2pdf/configuration.py
reddit2pdf/html2pdf.py
reddit2pdf/htmlwriter.py
reddit2pdf/json2html.py
reddit2pdf/library.py
reddit2pdf/reddit2pdf.py
reddit2pdf/templates/comments.html
reddit2pdf/templates/footer.html
reddit2pdf/templates/gallery.html
reddit2pdf/templates/header.html
reddit2pdf/templates/page.html
reddit2pdf/templates/post.html
reddit2pdf/templates/style.css
reddit2pdf/url2bdfr.py
reddit2pdf-1.1.2.dist-info/METADATA
reddit2pdf-1.1.2.dist-info/WHEEL
reddit2pdf-1.1.2.dist-info/entry_points.txt
reddit2pdf-1.1.2.dist-info/RECORD
